asedb/__init__.py
asedb/_version.txt
asedb/abstract.py
asedb/atoms_model.py
asedb/initialization.py
asedb/properties.py
asedb/time_utils.py
asedb/trajectory_model.py
asedb/utils.py
asedb/version.py
asedb-0.0.1.dist-info/LICENSE.txt
asedb-0.0.1.dist-info/METADATA
asedb-0.0.1.dist-info/WHEEL
asedb-0.0.1.dist-info/top_level.txt
asedb-0.0.1.dist-info/RECORD
