Metadata-Version: 2.1
Name: asedb
Version: 0.0.1
Summary: SQLAlchemy model for ASE Atoms objects
Home-page: https://gitlab.com/AlTy/asedb
Author: Alexander Tygesen
Author-email: atygesen@hotmail.com
License: MIT
Project-URL: Source, https://gitlab.com/AlTy/asedb
Classifier: Development Status :: 4 - Beta
Classifier: Programming Language :: Python
Requires-Python: >=3.8
License-File: LICENSE.txt
Requires-Dist: ase
Requires-Dist: sqlalchemy >2
Requires-Dist: python-dotenv
Requires-Dist: pendulum
Requires-Dist: packaging
Requires-Dist: numpy
Provides-Extra: postgres
Requires-Dist: psycopg2-binary ; extra == 'postgres'
Provides-Extra: test
Requires-Dist: pytest ; extra == 'test'
